{
    "fields": {
        "last_menstrual_period": {
            "label": "Tarehe ya mwisho wa kipindi cha hedhi",
            "type": "date",
            "dateFormat": "yy-mm-dd",
            "datepicker": {
                "hideIfNoPrevNextType": true,
                "yearRange": "2010:+10",
                "changeMonth": true,
                "changeYear": true
            }
        },
        "due_date": {
            "label": "Tarehe ya matarajio",
            "type": "date",
            "dateFormat": "yy-mm-dd",
            "datepicker": {
                "hideIfNoPrevNextType": true,
                "yearRange": "2010:+10",
                "changeMonth": true,
                "changeYear": true
            }
        },
        "date_gestationalage": {
            "type": "hidden"
        },
        "current_gestationalage_weeks": {
            "label": "wiki)",
            "type": "select"
        },
        "number_pregnancy": {
            "label": "Idadi ya ujauzito",
            "type": "select"
        },
        "pregnancy_test": {
            "label": "Positive Pregnancy Test?",
            "type": "radio",
            "enum": [
                "Yes",
                "No",
                "Unknown"
            ],
            "removeDefaultNone": true
        },
        "number_full_term_delivery": {
            "label": "Idadi ya kujifungua katika mda uliokamilika",
            "type": "select"
        },
        "number_pre_term_delivery": {
            "label": "Idadi ya kujifungua watoto wasiotimiza umri",
            "type": "select"
        },
        "number_miscarriage_abortion": {
            "label": "Idadi ya mimba zilizoharibika au kutolewa",
            "type": "select"
        },
        "number_live_birth": {
            "label": "Idadi ya waliozaliwa hai",
            "type": "select"
        },
        "weight_heaviest_infant": {
            "label": "Uzito takriban wa mtoto mchanga mzito uliejifungua awali",
            "type": "select"
        },
        "pregnancy_complications": {
            "label": "Matatizo katika ujauzito uliopita",
            "type": "checkbox"
        },
        "other_pregnancy_complications": {
            "label": "If Other Pregnancy Complication, Please Describe:"
        },
        "pregnancy_diseases": {
            "label": "Diseases:",
            "type": "checkbox"
        },
        "std_status": {
            "label": "Infected with STD",
            "type": "radio",
            "enum": [
                "Yes",
                "No",
                "Unknown"
            ],
            "removeDefaultNone": true
        },
        "std_treatment": {
            "label": "Being treated for STD",
            "type": "radio",
            "enum": [
                "Yes",
                "No",
                "Unknown"
            ],
            "removeDefaultNone": true
        },
        "hiv_status_prior_firstvisit": {
            "label": "Hadhi ya VVU",
            "type": "radio",
            "removeDefaultNone": true

        },
        "tested_hiv_firstvisit": {
            "label": "Tested for HIV on first visit?",
            "type": "radio",
            "enum": [
                "Yes",
                "No",
                "Unknown"
            ],
            "removeDefaultNone": true
        },
        "first_hiv_status": {
            "label": "Result if tested for HIV on first visit",
            "type": "radio",
            "removeDefaultNone": true

        },
        "second_hiv_test": {
            "label": "Tested positive by second HIV test?",
            "type": "radio",
            "enum": [
                "Yes",
                "No",
                "Unknown"
            ],
            "removeDefaultNone": true
        },
        "refer_ctc": {
            "label": "Referred to CTC?",
            "type": "radio",
            "enum": [
                "Yes",
                "No",
                "Unknown"
            ],
            "removeDefaultNone": true
        },
        "partner_hiv": {
            "label": "Partner tested for HIV in clinic?",
            "type": "radio",
            "enum": [
                "Yes",
                "No",
                "Unknown"
            ],
            "removeDefaultNone": true
        },
        "partner_positive": {
            "label": "Partner tested positive for HIV?",
            "type": "radio",
            "enum": [
                "Yes",
                "No",
                "Unknown"
            ],
            "removeDefaultNone": true
        },
        "discordant_couple": {
            "label": "Discordant couple?",
            "type": "radio",
            "enum": [
                "Yes",
                "No",
                "Unknown"
            ],
            "removeDefaultNone": true
        },
        "combo_drugs": {
            "label": "Patient recieved PMCTC combo drugs?",
            "type": "radio",
            "enum": [
                "Yes",
                "No",
                "Unknown"
            ],
            "removeDefaultNone": true
        },
        "art_drugs": {
            "label": "Patient using ART?",
            "type": "radio",
            "enum": [
                "Yes",
                "No",
                "Unknown"
            ],
            "removeDefaultNone": true
        },
        "ctx_given": {
            "label": "Patient given CTX?",
            "type": "radio",
            "enum": [
                "Yes",
                "No",
                "Unknown"
            ],
            "removeDefaultNone": true
        },
        "counsel_feeding": {
            "label": "Counseled on how to feed the baby?",
            "type": "radio",
            "enum": [
                "Yes",
                "No",
                "Unknown"
            ],
            "removeDefaultNone": true
        },
        "syphillus_test": {
            "label": "Tested for Syphillus",
            "type": "radio",
            "enum": [
                "Yes",
                "No",
                "Unknown"
            ],
            "removeDefaultNone": true
        },
        "syphillus_status": {
            "label": "Infected with Syphillus",
            "type": "radio",
            "enum": [
                "Yes",
                "No",
                "Unknown"
            ],
            "removeDefaultNone": true
        },
        "syphillus_treatment": {
            "label": "Being treated for Syphillus",
            "type": "radio",
            "enum": [
                "Yes",
                "No",
                "Unknown"
            ],
            "removeDefaultNone": true
        },
        "partner_std": {
            "label": "Partner infected with STD",
            "type": "radio",
            "enum": [
                "Yes",
                "No",
                "Unknown"
            ],
            "removeDefaultNone": true
        },
        "partner_std_treatment": {
            "label": "Partner being treated for STD",
            "type": "radio",
            "enum": [
                "Yes",
                "No",
                "Unknown"
            ],
            "removeDefaultNone": true
        },
        "partner_syphillus_test": {
            "label": "Partner infected with Syphillus",
            "type": "radio",
            "enum": [
                "Yes",
                "No",
                "Unknown"
            ],
            "removeDefaultNone": true
        },
        "partner_syphillus_status": {
            "label": "Partner infected with Syphillus",
            "type": "radio",
            "enum": [
                "Yes",
                "No",
                "Unknown"
            ],
            "removeDefaultNone": true
        },
        "partner_syphillus_treatment": {
            "label": "Partner being treated for Syphillus",
            "type": "radio",
            "enum": [
                "Yes",
                "No",
                "Unknown"
            ],
            "removeDefaultNone": true
        },
        "malaria_test": {
            "label": "Tested for malaria?",
            "type": "radio",
            "enum": [
                "Yes",
                "No",
                "Unknown"
            ],
            "removeDefaultNone": true
        },
        "malar_pos": {
            "label": "Tested positive for malaria?",
            "type": "radio",
            "enum": [
                "Yes",
                "No",
                "Unknown"
            ],
            "removeDefaultNone": true
        },
        "bednet_voucher": {
            "label": "Given voucher for free bednet?",
            "type": "radio",
            "enum": [
                "Yes",
                "No",
                "Unknown"
            ],
            "removeDefaultNone": true
        },
        "ipt1": {
            "label": "Given IPT1?",
            "type": "radio",
            "enum": [
                "Yes",
                "No",
                "Unknown"
            ],
            "removeDefaultNone": true
        },
        "ipt2": {
            "label": "Given IPT2?",
            "type": "radio",
            "enum": [
                "Yes",
                "No",
                "Unknown"
            ],
            "removeDefaultNone": true
        },
        "bp_systolic": {
            "label": "BP Sistolik",
            "type": "number"
        },
        "bp_diastolic": {
            "label": "BP Diyastolik",
            "type": "number"
        },
        "anemia_severe": {
            "label": ">8.5g/dl",
            "type": "select"
        },
        "symptoms": {
            "label": "Dalili",
            "type": "checkbox"
        },
        "tt2plus_vaccine": {
            "label": "Received vaccination of TT2+",
            "type": "radio",
            "enum": [
                "Yes",
                "No",
                "Unknown"
            ],
            "removeDefaultNone": true
        },
        "other_symptoms": {
            "label": "If Other Symptom, Please Describe: (Dalili nyingine)"
        },
        "fundal_height": {
            "label": "cm)",
            "type": "select"
        },
        "fetal_heart_rate": {
            "label": "Mapigo ya moyo ya Kijusi",
            "type": "select"
        },
        "treatment_given": {
            "label": "If Any Treatment Given, Please Describe:",
            "type": "textarea"
        },
        "iron_tablets": {
            "label": "Given iron tablets?",
            "type": "radio",
            "enum": [
                "Yes",
                "No",
                "Unknown"
            ],
            "removeDefaultNone": true
        },
        "alben_tablets": {
            "label": "Given albendazole?",
            "type": "radio",
            "enum": [
                "Yes",
                "No",
                "Unknown"
            ],
            "removeDefaultNone": true
        },
        "notes": {
            "label": "Examination Findings:",
            "type": "textarea"
        },
        "admission": {
            "label": "Admission Required Today?",
            "type": "radio",
            "enum": [
                "Yes",
                "No",
                "Unknown"
            ],
            "removeDefaultNone": true
        },
        "referral": {
            "label": "Referral?",
            "type": "radio",
            "enum": [
                "Yes",
                "No",
                "Unknown"
            ],
            "removeDefaultNone": true
        },
        "referred_ctc": {
            "label": "Mama alipewa rufaa kwenda CTC?",
            "type": "radio",
            "enum": [
                "Yes",
                "No",
                "Unknown"
            ],
            "removeDefaultNone": true
        },
        "in_labor": {
            "label": "Laboring Now?",
            "type": "radio",
            "enum": [
                "Yes",
                "No",
                "Unknown"
            ],
            "removeDefaultNone": true
        }
    }
}