{
    "title": "3.5.1 Deliveries at the Health center",
    "type": "object",
    "properties": {
        "eutocic_deliveries": {
            "line_number": "1",
            "fr": "Accouchements eutociques",
            "en": "Eutocic deliveries"
        },
        "dystocic_deliveries": {
            "line_number": "2",
            "fr": "Accouchements dystociques",
            "en": "Dystocic deliveries"
        },
        "including_20_yrs": {
            "line_number": "3",
            "fr": "Dont âgés de < 20 an",
            "en": "Including < 20 yrs"
        },
        "including_watched_out": {
            "line_number": "4",
            "fr": "Dont surveillés",
            "en": "Including watched out"
        },
        "mother_who_beneficiated_gatpa": {
            "line_number": "5",
            "fr": "Mère ayant bénéficié de la GATPA",
            "en": "Mother who beneficiated GATPA"
        }
    },
    "definitions": {
        "columns": {
            "as": {
                "fr": "AS",
                "en": "AS"
            },
            "has": {
                "fr": "HAS",
                "en": "HAS"
            },
            "hz": {
                "fr": "HZ",
                "en": "HZ"
            },
            "total": {
                "fr": "TOTAL",
                "en": "TOTAL"
            }
        }
    },
    "parent": "report_pregnant"
}
